{
  "formatVersion": 1,
  "database": {
    "version": 4,
    "identityHash": "f4fa179d633c9d66215414f108969395",
    "entities": [
      {
        "tableName": "cve",
        "createSql": "CREATE TABLE IF NOT EXISTS `${TABLE_NAME}` (`id` TEXT NOT NULL, `summary` TEXT NOT NULL, `publishedEpochSec` INTEGER, `source` TEXT NOT NULL, `score` INTEGER NOT NULL, `tagsCsv` TEXT NOT NULL, `seen` INTEGER NOT NULL, `acknowledged` INTEGER NOT NULL, `insertedAtEpochMs` INTEGER NOT NULL, PRIMARY KEY(`id`))",
        "fields": [
          {
            "fieldPath": "id",
            "columnName": "id",
            "affinity": "TEXT",
            "notNull": true
          },
          {
            "fieldPath": "summary",
            "columnName": "summary",
            "affinity": "TEXT",
            "notNull": true
          },
          {
            "fieldPath": "publishedEpochSec",
            "columnName": "publishedEpochSec",
            "affinity": "INTEGER",
            "notNull": false
          },
          {
            "fieldPath": "source",
            "columnName": "source",
            "affinity": "TEXT",
            "notNull": true
          },
          {
            "fieldPath": "score",
            "columnName": "score",
            "affinity": "INTEGER",
            "notNull": true
          },
          {
            "fieldPath": "tagsCsv",
            "columnName": "tagsCsv",
            "affinity": "TEXT",
            "notNull": true
          },
          {
            "fieldPath": "seen",
            "columnName": "seen",
            "affinity": "INTEGER",
            "notNull": true
          },
          {
            "fieldPath": "acknowledged",
            "columnName": "acknowledged",
            "affinity": "INTEGER",
            "notNull": true
          },
          {
            "fieldPath": "insertedAtEpochMs",
            "columnName": "insertedAtEpochMs",
            "affinity": "INTEGER",
            "notNull": true
          }
        ],
        "primaryKey": {
          "autoGenerate": false,
          "columnNames": [
            "id"
          ]
        },
        "indices": [],
        "foreignKeys": []
      },
      {
        "tableName": "kev",
        "createSql": "CREATE TABLE IF NOT EXISTS `${TABLE_NAME}` (`cveId` TEXT NOT NULL, `dateAddedEpochSec` INTEGER, PRIMARY KEY(`cveId`))",
        "fields": [
          {
            "fieldPath": "cveId",
            "columnName": "cveId",
            "affinity": "TEXT",
            "notNull": true
          },
          {
            "fieldPath": "dateAddedEpochSec",
            "columnName": "dateAddedEpochSec",
            "affinity": "INTEGER",
            "notNull": false
          }
        ],
        "primaryKey": {
          "autoGenerate": false,
          "columnNames": [
            "cveId"
          ]
        },
        "indices": [],
        "foreignKeys": []
      },
      {
        "tableName": "favorites",
        "createSql": "CREATE TABLE IF NOT EXISTS `${TABLE_NAME}` (`id` INTEGER PRIMARY KEY AUTOINCREMENT NOT NULL, `label` TEXT NOT NULL, `value` TEXT NOT NULL, `createdAt` INTEGER NOT NULL)",
        "fields": [
          {
            "fieldPath": "id",
            "columnName": "id",
            "affinity": "INTEGER",
            "notNull": true
          },
          {
            "fieldPath": "label",
            "columnName": "label",
            "affinity": "TEXT",
            "notNull": true
          },
          {
            "fieldPath": "value",
            "columnName": "value",
            "affinity": "TEXT",
            "notNull": true
          },
          {
            "fieldPath": "createdAt",
            "columnName": "createdAt",
            "affinity": "INTEGER",
            "notNull": true
          }
        ],
        "primaryKey": {
          "autoGenerate": true,
          "columnNames": [
            "id"
          ]
        },
        "indices": [],
        "foreignKeys": []
      },
      {
        "tableName": "app_baseline",
        "createSql": "CREATE TABLE IF NOT EXISTS `${TABLE_NAME}` (`packageName` TEXT NOT NULL, `certSha256` TEXT NOT NULL, `versionCode` INTEGER NOT NULL, `versionName` TEXT, `isSystemApp` INTEGER NOT NULL, `installerPackage` TEXT, `apkPath` TEXT, `firstSeenAt` INTEGER NOT NULL, `lastSeenAt` INTEGER NOT NULL, `lastCertChangeAt` INTEGER NOT NULL, `previousCertSha256` TEXT, `scanCount` INTEGER NOT NULL, `permissionSetHash` TEXT, `highRiskPermissions` TEXT, `exportedActivityCount` INTEGER NOT NULL, `exportedServiceCount` INTEGER NOT NULL, `exportedReceiverCount` INTEGER NOT NULL, `exportedProviderCount` INTEGER NOT NULL, `unprotectedExportedCount` INTEGER NOT NULL, PRIMARY KEY(`packageName`))",
        "fields": [
          {
            "fieldPath": "packageName",
            "columnName": "packageName",
            "affinity": "TEXT",
            "notNull": true
          },
          {
            "fieldPath": "certSha256",
            "columnName": "certSha256",
            "affinity": "TEXT",
            "notNull": true
          },
          {
            "fieldPath": "versionCode",
            "columnName": "versionCode",
            "affinity": "INTEGER",
            "notNull": true
          },
          {
            "fieldPath": "versionName",
            "columnName": "versionName",
            "affinity": "TEXT",
            "notNull": false
          },
          {
            "fieldPath": "isSystemApp",
            "columnName": "isSystemApp",
            "affinity": "INTEGER",
            "notNull": true
          },
          {
            "fieldPath": "installerPackage",
            "columnName": "installerPackage",
            "affinity": "TEXT",
            "notNull": false
          },
          {
            "fieldPath": "apkPath",
            "columnName": "apkPath",
            "affinity": "TEXT",
            "notNull": false
          },
          {
            "fieldPath": "firstSeenAt",
            "columnName": "firstSeenAt",
            "affinity": "INTEGER",
            "notNull": true
          },
          {
            "fieldPath": "lastSeenAt",
            "columnName": "lastSeenAt",
            "affinity": "INTEGER",
            "notNull": true
          },
          {
            "fieldPath": "lastCertChangeAt",
            "columnName": "lastCertChangeAt",
            "affinity": "INTEGER",
            "notNull": true
          },
          {
            "fieldPath": "previousCertSha256",
            "columnName": "previousCertSha256",
            "affinity": "TEXT",
            "notNull": false
          },
          {
            "fieldPath": "scanCount",
            "columnName": "scanCount",
            "affinity": "INTEGER",
            "notNull": true
          },
          {
            "fieldPath": "permissionSetHash",
            "columnName": "permissionSetHash",
            "affinity": "TEXT",
            "notNull": false
          },
          {
            "fieldPath": "highRiskPermissions",
            "columnName": "highRiskPermissions",
            "affinity": "TEXT",
            "notNull": false
          },
          {
            "fieldPath": "exportedActivityCount",
            "columnName": "exportedActivityCount",
            "affinity": "INTEGER",
            "notNull": true
          },
          {
            "fieldPath": "exportedServiceCount",
            "columnName": "exportedServiceCount",
            "affinity": "INTEGER",
            "notNull": true
          },
          {
            "fieldPath": "exportedReceiverCount",
            "columnName": "exportedReceiverCount",
            "affinity": "INTEGER",
            "notNull": true
          },
          {
            "fieldPath": "exportedProviderCount",
            "columnName": "exportedProviderCount",
            "affinity": "INTEGER",
            "notNull": true
          },
          {
            "fieldPath": "unprotectedExportedCount",
            "columnName": "unprotectedExportedCount",
            "affinity": "INTEGER",
            "notNull": true
          }
        ],
        "primaryKey": {
          "autoGenerate": false,
          "columnNames": [
            "packageName"
          ]
        },
        "indices": [],
        "foreignKeys": []
      }
    ],
    "views": [],
    "setupQueries": [
      "CREATE TABLE IF NOT EXISTS room_master_table (id INTEGER PRIMARY KEY,identity_hash TEXT)",
      "INSERT OR REPLACE INTO room_master_table (id,identity_hash) VALUES(42, 'f4fa179d633c9d66215414f108969395')"
    ]
  }
}